spirit_extras/__init__.py
spirit_extras/calculation_folder.py
spirit_extras/chain_io.py
spirit_extras/configurations.py
spirit_extras/data.py
spirit_extras/dependency_gatherer.py
spirit_extras/gneb_workflow.py
spirit_extras/import_spirit.py
spirit_extras/memory_monitor.py
spirit_extras/plotting.py
spirit_extras/post_processing.py
spirit_extras/pyvista_plotting.py
spirit_extras/util.py
spirit_extras-0.0.35.dist-info/LICENSE
spirit_extras-0.0.35.dist-info/METADATA
spirit_extras-0.0.35.dist-info/WHEEL
spirit_extras-0.0.35.dist-info/top_level.txt
spirit_extras-0.0.35.dist-info/RECORD
