Metadata-Version: 2.1
Name: spirit-extras
Version: 0.0.35
Summary: Package to be used with the magnetism simulation tool spirit
Home-page: https://github.com/msallermann/spirit_extras
Author: Moritz Sallermann
Author-email: m.sallermann@fz-juelich.de
Classifier: Programming Language :: Python :: 3
Classifier: License :: OSI Approved :: MIT License
Classifier: Operating System :: OS Independent
Requires-Python: >=3.7
License-File: LICENSE
Requires-Dist: numpy
Requires-Dist: pyvista
Requires-Dist: anytree
Requires-Dist: termcolor
Requires-Dist: PyYAML
Requires-Dist: toml
Requires-Dist: pillow
